dnnf/__init__.py
dnnf/__main__.py
dnnf/__version__.py
dnnf/backends.py
dnnf/cli.py
dnnf/falsifier.py
dnnf/model.py
dnnf/pytorch.py
dnnf/reduction.py
dnnf/utils.py
dnnf-0.1.7.dist-info/entry_points.txt
dnnf-0.1.7.dist-info/LICENSE
dnnf-0.1.7.dist-info/WHEEL
dnnf-0.1.7.dist-info/METADATA
dnnf-0.1.7.dist-info/RECORD
