Metadata-Version: 2.1
Name: dnnf
Version: 0.1.7
Summary: dnnf - dnn property falsification
Keywords: DNN,neural network,falsification
Author-email: David Shriver <dls2fc@virginia.edu>
Requires-Python: >=3.7
Classifier: License :: OSI Approved :: MIT License
Requires-Dist: dnnv~=0.6.0
Requires-Dist: numpy>=1.20,<1.22
Requires-Dist: onnx>=1.8,<1.11
Requires-Dist: scipy~=1.7
Requires-Dist: torch~=1.6
Requires-Dist: torchvision~=0.7
Requires-Dist: cleverhans~=4.0 ; extra == "all"
Requires-Dist: foolbox~=3.3 ; extra == "all"
Requires-Dist: black~=22.3 ; extra == "all"
Requires-Dist: isort~=5.10 ; extra == "all"
Requires-Dist: mypy~=0.950 ; extra == "all"
Requires-Dist: sphinx~=4.5 ; extra == "all"
Requires-Dist: furo~=2022.4 ; extra == "all"
Requires-Dist: coverage~=5.5 ; extra == "all"
Requires-Dist: pytest~=6.2 ; extra == "all"
Requires-Dist: cleverhans~=4.0 ; extra == "cleverhans"
Requires-Dist: black~=22.3 ; extra == "dev"
Requires-Dist: isort~=5.10 ; extra == "dev"
Requires-Dist: mypy~=0.950 ; extra == "dev"
Requires-Dist: sphinx~=4.5 ; extra == "docs"
Requires-Dist: furo~=2022.4 ; extra == "docs"
Requires-Dist: foolbox~=3.3 ; extra == "foolbox"
Requires-Dist: coverage~=5.5 ; extra == "test"
Requires-Dist: pytest~=6.2 ; extra == "test"
Project-URL: Documentation, https://dnnf.readthedocs.io/en/latest/
Project-URL: Source, https://github.com/dlshriver/dnnf
Provides-Extra: all
Provides-Extra: cleverhans
Provides-Extra: dev
Provides-Extra: docs
Provides-Extra: foolbox
Provides-Extra: test
